bonndit/__init__.py
bonndit/base.py
bonndit/constants.py
bonndit/dki.py
bonndit/gradients.py
bonndit/io.py
bonndit/multivoxel.py
bonndit/shdeconv.py
bonndit/shoredeconv.py
bonndit/michi/__init__.py
bonndit/michi/dwmri.py
bonndit/michi/esh.py
bonndit/michi/fields.py
bonndit/michi/mmath.py
bonndit/michi/nrrd.py
bonndit/michi/shore.py
bonndit/michi/storage.py
bonndit/michi/tensor.py
bonndit/michi/vector.py
bonndit-0.1.2.data/scripts/kurtosis
bonndit-0.1.2.data/scripts/mtdeconv
bonndit-0.1.2.data/scripts/stdeconv
bonndit-0.1.2.dist-info/AUTHORS.rst
bonndit-0.1.2.dist-info/LICENSE
bonndit-0.1.2.dist-info/METADATA
bonndit-0.1.2.dist-info/WHEEL
bonndit-0.1.2.dist-info/top_level.txt
bonndit-0.1.2.dist-info/RECORD
