Metadata-Version: 2.1
Name: bonndit
Version: 0.1.2
Summary: The bonndit package contains the latest diffusion imaging tools developed at the University of Bonn.
Home-page: https://github.com/MedVisBonn/bonndit
Author: Olivier Morelle
Author-email: morelle@uni-bonn.de
License: GNU General Public License v3
Keywords: bonndit
Platform: UNKNOWN
Classifier: Topic :: Scientific/Engineering
Classifier: Development Status :: 3 - Alpha
Classifier: Intended Audience :: Science/Research
Classifier: License :: OSI Approved :: GNU General Public License v3 (GPLv3)
Classifier: Natural Language :: English
Classifier: Programming Language :: Python :: 3.5
Classifier: Programming Language :: Python :: 3.6
Classifier: Programming Language :: Python :: 3.7
Requires-Dist: nibabel
Requires-Dist: numpy
Requires-Dist: pandas
Requires-Dist: dipy
Requires-Dist: scipy
Requires-Dist: tqdm
Requires-Dist: cvxopt
Requires-Dist: mpmath
